tiktoken/__init__.py
tiktoken/_educational.py
tiktoken/_tiktoken.cpython-312.so
tiktoken/core.py
tiktoken/load.py
tiktoken/model.py
tiktoken/py.typed
tiktoken/registry.py
tiktoken_ext/openai_public.py
tiktoken_qpython-0.9.0.1.dist-info/METADATA
tiktoken_qpython-0.9.0.1.dist-info/WHEEL
tiktoken_qpython-0.9.0.1.dist-info/top_level.txt
tiktoken_qpython-0.9.0.1.dist-info/RECORD
